Lab-of-Digital-Logic-Design/3/adder.v
`timescale 1ns/100ps

module FA(s,p,g,co,a,b,ci);
    output s,p,g,co;
    input a,b,ci;
    wire w1,w2,w3;

    // lookahead
    or #15 G1(p,a,b);
    and #10 G2(g,a,b);
    
    // sum
    xor #20 G3(w1,a,b);
    xor #20 G4(s,w1,ci);
    
    // carry
    and #10 G5(w2,a,ci);
    and #10 G6(w3,b,ci);
    or #20 G7(co,g,w2,w3);
endmodule

module t_FA;
    wire s,p,g,co;
    reg a,b,ci;

    FA addr(s,p,g,co,a,b,ci);

    initial begin
        a = 1'b0; b = 1'b0; ci = 1'b0;
        #100 a = 1'b0; b = 1'b0; ci = 1'b1;
        #100 a = 1'b0; b = 1'b1; ci = 1'b0;
        #100 a = 1'b0; b = 1'b1; ci = 1'b1;
        #100 a = 1'b1; b = 1'b0; ci = 1'b0;
        #100 a = 1'b1; b = 1'b0; ci = 1'b1;
        #100 a = 1'b1; b = 1'b1; ci = 1'b0;
        #100 a = 1'b1; b = 1'b1; ci = 1'b1;
    end

    // initial #1000 $finish;
    initial $dumpvars;  

endmodule

module RCA_16 (
    co, s, c0, a, b
);
    output co;
    output [15:0] s;
    input c0;
    input [15:0] a,b;
    wire [16:0] c;

    assign c[0] = c0;
    assign co = c[16];
    
    genvar i;
    generate
        for (i = 0; i<16 ; i = i + 1 ) begin
            FA adder (.s(s[i]), .co(c[i+1]), .a(a[i]), .b(b[i]), .ci(c[i]) );        
        end
    endgenerate
    
endmodule

module t_RCA_16;

    wire co;
    wire [15:0] s;
    reg [15:0] a,b;

    RCA_16 rca (co,s,1'b0,a,b);

    initial begin
        a = 16'h1234; b = 16'h5678;
    end
    initial $dumpvars;
    // initial #500 $finish;

endmodule

module CLA_4 (
    co, s, po, go, c0, a, b
);

    output co, po, go;
    output [3:0] s;
    input [3:0] a, b;
    input c0;
    wire [4:0] c,p,g;

    assign co = c[4];
    assign c[0] = c0;

    genvar i;
    generate
        for (i = 0;i<4 ;i=i+1 ) begin
            FA addr(.s(s[i]),.p(p[i]),.g(g[i]),.a(a[i]),.b(b[i]),.ci(c[i]));
        end
    endgenerate

    // LCU
    wire wp0c0,wp1g0,wp1p0c0, wp2g1, wp2p1g0, wp2p1p0c0;

    and #10 p0c0(wp0c0, p[0], c[0]);
    or #15 c1(c[1], g[0], wp0c0);
    
    and #10 p1g0(wp1g0, p[1], g[0]);
    and #15 p1p0c0(wp1p0c0, p[1], p[0], c[0]);
    or #20 c2(c[2], g[1], wp1p0c0, wp1g0);

    and #10 p2g1(wp2g1, p[2], g[1]);
    and #15 p2p1g0(wp2p1g0, p[2], p[1], g[0]);
    and #20 p2p1p0c0(wp2p1p0c0, p[2], p[1], p[0], c[0]);
    or #25 c3(c[3], g[2], wp2g1, wp2p1g0, wp2p1p0c0);
    
    and #10 p3g2(wp3g2, p[3], g[2]);
    and #15 p3p2g1(wp3p2g1, p[3], p[2], g[1]);
    and #20 p3p2p1g0(wp3p2p1g0, p[3], p[2], p[1], g[0]);
    and #25 p3p2p1p0c0(wp3p2p1p0c0, p[3], p[2], p[1], p[0], c[0]);
    or #30 c4(c[4], g[3], wp3g2,wp3p2g1,wp3p2p1g0,wp3p2p1p0c0);

    and #20 Gpo(po, p[3], p[2], p[1], p[0]);

    or #25 Ggo(go, g[3], wp3g2, wp3p2g1, wp3p2p1g0);

endmodule

module t_CLA_4;
    
    wire [3:0] s;
    wire p, g, c;
    reg [3:0] a,b;

    CLA_4 cla(c, s, p, g, 1'b0, a, b);
    
    initial begin
        a = 4'h3; b = 4'h7;
        #200 a = 4'h9; b = 4'h9;
        #200 a = 4'h8; b = 4'h7;
    end
    initial $dumpvars;
    // initial #600 $finish;

endmodule

module CLA_16 (
    co, s, po, go, ci, a, b
);
    output co, po, go;
    output [15:0] s;
    input ci;
    input [15:0] a,b;

    wire [3:0] p,g;
    wire [4:0] c;
    assign c[0] = ci;
    assign co = c[4];

    genvar i;
    generate
        for (i = 0;i<4 ;i=i+1 ) begin
            CLA_4 adder(.s(s[4*(i+1)-1:4*i]), .po(p[i]), .go(g[i]), .a(a[4*(i+1)-1:4*i]), .b(b[4*(i+1)-1:4*i]), .c0(c[i]));
        end
    endgenerate

    //LCU
    wire wp0c0,wp1g0,wp1p0c0, wp2g1, wp2p1g0, wp2p1p0c0;

    and #10 p0c0(wp0c0, p[0], c[0]);
    or #15 c1(c[1], g[0], wp0c0);
    
    and #10 p1g0(wp1g0, p[1], g[0]);
    and #15 p1p0c0(wp1p0c0, p[1], p[0], c[0]);
    or #20 c2(c[2], g[1], wp1p0c0, wp1g0);

    and #10 p2g1(wp2g1, p[2], g[1]);
    and #15 p2p1g0(wp2p1g0, p[2], p[1], g[0]);
    and #20 p2p1p0c0(wp2p1p0c0, p[2], p[1], p[0], c[0]);
    or #25 c3(c[3], g[2], wp2g1, wp2p1g0, wp2p1p0c0);
    
    and #10 p3g2(wp3g2, p[3], g[2]);
    and #15 p3p2g1(wp3p2g1, p[3], p[2], g[1]);
    and #20 p3p2p1g0(wp3p2p1g0, p[3], p[2], p[1], g[0]);
    and #25 p3p2p1p0c0(wp3p2p1p0c0, p[3], p[2], p[1], p[0], c[0]);
    or #30 c4(c[4], g[3], wp3g2,wp3p2g1,wp3p2p1g0,wp3p2p1p0c0);

    and #20 Gpo(po, p[3], p[2], p[1], p[0]);

    or #25 Ggo(go, g[3], wp3g2, wp3p2g1, wp3p2p1g0);
    
endmodule

module t_CLA_16;
    
    wire [15:0] s;
    wire p, g, c;
    reg [15:0] a,b;

    CLA_16 cla(c, s, p, g, 1'b0, a, b);
    
    initial begin
        a = 16'h9823; b = 16'h5407;
        #250 a = 16'h9527; b = 16'h9678;
        #250 a = 16'h8888; b = 16'h7777;
    end
    initial $dumpvars;
    // initial #800 $finish;

endmodule

module compare_CLA_RCA;

    wire c_cla, c_rca;
    wire [15:0] s_cla, s_rca;
    reg [15:0] a, b;

    CLA_16 cla(.co(c_cla), .s(s_cla), .ci(1'b0), .a(a), .b(b));
    RCA_16 rca(.co(c_rca), .s(s_rca), .c0(1'b0), .a(a), .b(b));

    initial begin
        a = 16'h6677; b = 16'h2233;
        #3000 a = 16'hABCD; b = 16'hF39C;
        #3000 a = 16'h8888; b = 16'h7777;
    end
    initial $dumpvars;
    initial #9000 $finish;

endmodule

Lab-of-Digital-Logic-Design/3/dump.vcd
$date
	Thu Oct 21 01:53:39 2021
$end
$version
	Icarus Verilog
$end
$timescale
	100ps
$end
$scope module t_RCA_16 $end
$var wire 16 ! s [15:0] $end
$var wire 1 " co $end
$var reg 16 # a [15:0] $end
$var reg 16 $ b [15:0] $end
$scope module rca $end
$var wire 16 % a [15:0] $end
$var wire 16 & b [15:0] $end
$var wire 1 ' c0 $end
$var wire 16 ( s [15:0] $end
$var wire 1 " co $end
$var wire 17 ) c [16:0] $end
$scope begin genblk1[0] $end
$scope module adder $end
$var wire 1 * a $end
$var wire 1 + b $end
$var wire 1 , ci $end
$var wire 1 - co $end
$var wire 1 . g $end
$var wire 1 / p $end
$var wire 1 0 s $end
$var wire 1 1 w1 $end
$var wire 1 2 w2 $end
$var wire 1 3 w3 $end
$upscope $end
$upscope $end
$scope begin genblk1[1] $end
$scope module adder $end
$var wire 1 4 a $end
$var wire 1 5 b $end
$var wire 1 6 ci $end
$var wire 1 7 co $end
$var wire 1 8 g $end
$var wire 1 9 p $end
$var wire 1 : s $end
$var wire 1 ; w1 $end
$var wire 1 < w2 $end
$var wire 1 = w3 $end
$upscope $end
$upscope $end
$scope begin genblk1[2] $end
$scope module adder $end
$var wire 1 > a $end
$var wire 1 ? b $end
$var wire 1 @ ci $end
$var wire 1 A co $end
$var wire 1 B g $end
$var wire 1 C p $end
$var wire 1 D s $end
$var wire 1 E w1 $end
$var wire 1 F w2 $end
$var wire 1 G w3 $end
$upscope $end
$upscope $end
$scope begin genblk1[3] $end
$scope module adder $end
$var wire 1 H a $end
$var wire 1 I b $end
$var wire 1 J ci $end
$var wire 1 K co $end
$var wire 1 L g $end
$var wire 1 M p $end
$var wire 1 N s $end
$var wire 1 O w1 $end
$var wire 1 P w2 $end
$var wire 1 Q w3 $end
$upscope $end
$upscope $end
$scope begin genblk1[4] $end
$scope module adder $end
$var wire 1 R a $end
$var wire 1 S b $end
$var wire 1 T ci $end
$var wire 1 U co $end
$var wire 1 V g $end
$var wire 1 W p $end
$var wire 1 X s $end
$var wire 1 Y w1 $end
$var wire 1 Z w2 $end
$var wire 1 [ w3 $end
$upscope $end
$upscope $end
$scope begin genblk1[5] $end
$scope module adder $end
$var wire 1 \ a $end
$var wire 1 ] b $end
$var wire 1 ^ ci $end
$var wire 1 _ co $end
$var wire 1 ` g $end
$var wire 1 a p $end
$var wire 1 b s $end
$var wire 1 c w1 $end
$var wire 1 d w2 $end
$var wire 1 e w3 $end
$upscope $end
$upscope $end
$scope begin genblk1[6] $end
$scope module adder $end
$var wire 1 f a $end
$var wire 1 g b $end
$var wire 1 h ci $end
$var wire 1 i co $end
$var wire 1 j g $end
$var wire 1 k p $end
$var wire 1 l s $end
$var wire 1 m w1 $end
$var wire 1 n w2 $end
$var wire 1 o w3 $end
$upscope $end
$upscope $end
$scope begin genblk1[7] $end
$scope module adder $end
$var wire 1 p a $end
$var wire 1 q b $end
$var wire 1 r ci $end
$var wire 1 s co $end
$var wire 1 t g $end
$var wire 1 u p $end
$var wire 1 v s $end
$var wire 1 w w1 $end
$var wire 1 x w2 $end
$var wire 1 y w3 $end
$upscope $end
$upscope $end
$scope begin genblk1[8] $end
$scope module adder $end
$var wire 1 z a $end
$var wire 1 { b $end
$var wire 1 | ci $end
$var wire 1 } co $end
$var wire 1 ~ g $end
$var wire 1 !" p $end
$var wire 1 "" s $end
$var wire 1 #" w1 $end
$var wire 1 $" w2 $end
$var wire 1 %" w3 $end
$upscope $end
$upscope $end
$scope begin genblk1[9] $end
$scope module adder $end
$var wire 1 &" a $end
$var wire 1 '" b $end
$var wire 1 (" ci $end
$var wire 1 )" co $end
$var wire 1 *" g $end
$var wire 1 +" p $end
$var wire 1 ," s $end
$var wire 1 -" w1 $end
$var wire 1 ." w2 $end
$var wire 1 /" w3 $end
$upscope $end
$upscope $end
$scope begin genblk1[10] $end
$scope module adder $end
$var wire 1 0" a $end
$var wire 1 1" b $end
$var wire 1 2" ci $end
$var wire 1 3" co $end
$var wire 1 4" g $end
$var wire 1 5" p $end
$var wire 1 6" s $end
$var wire 1 7" w1 $end
$var wire 1 8" w2 $end
$var wire 1 9" w3 $end
$upscope $end
$upscope $end
$scope begin genblk1[11] $end
$scope module adder $end
$var wire 1 :" a $end
$var wire 1 ;" b $end
$var wire 1 <" ci $end
$var wire 1 =" co $end
$var wire 1 >" g $end
$var wire 1 ?" p $end
$var wire 1 @" s $end
$var wire 1 A" w1 $end
$var wire 1 B" w2 $end
$var wire 1 C" w3 $end
$upscope $end
$upscope $end
$scope begin genblk1[12] $end
$scope module adder $end
$var wire 1 D" a $end
$var wire 1 E" b $end
$var wire 1 F" ci $end
$var wire 1 G" co $end
$var wire 1 H" g $end
$var wire 1 I" p $end
$var wire 1 J" s $end
$var wire 1 K" w1 $end
$var wire 1 L" w2 $end
$var wire 1 M" w3 $end
$upscope $end
$upscope $end
$scope begin genblk1[13] $end
$scope module adder $end
$var wire 1 N" a $end
$var wire 1 O" b $end
$var wire 1 P" ci $end
$var wire 1 Q" co $end
$var wire 1 R" g $end
$var wire 1 S" p $end
$var wire 1 T" s $end
$var wire 1 U" w1 $end
$var wire 1 V" w2 $end
$var wire 1 W" w3 $end
$upscope $end
$upscope $end
$scope begin genblk1[14] $end
$scope module adder $end
$var wire 1 X" a $end
$var wire 1 Y" b $end
$var wire 1 Z" ci $end
$var wire 1 [" co $end
$var wire 1 \" g $end
$var wire 1 ]" p $end
$var wire 1 ^" s $end
$var wire 1 _" w1 $end
$var wire 1 `" w2 $end
$var wire 1 a" w3 $end
$upscope $end
$upscope $end
$scope begin genblk1[15] $end
$scope module adder $end
$var wire 1 b" a $end
$var wire 1 c" b $end
$var wire 1 d" ci $end
$var wire 1 e" co $end
$var wire 1 f" g $end
$var wire 1 g" p $end
$var wire 1 h" s $end
$var wire 1 i" w1 $end
$var wire 1 j" w2 $end
$var wire 1 k" w3 $end
$upscope $end
$upscope $end
$upscope $end
$upscope $end
$enddefinitions $end
#0
$dumpvars
xk"
xj"
xi"
xh"
xg"
xf"
xe"
xd"
0c"
0b"
xa"
x`"
x_"
x^"
x]"
x\"
x["
xZ"
1Y"
0X"
xW"
xV"
xU"
xT"
xS"
xR"
xQ"
xP"
0O"
0N"
xM"
xL"
xK"
xJ"
xI"
xH"
xG"
xF"
1E"
1D"
xC"
xB"
xA"
x@"
x?"
x>"
x="
x<"
0;"
0:"
x9"
x8"
x7"
x6"
x5"
x4"
x3"
x2"
11"
00"
x/"
x."
x-"
x,"
x+"
x*"
x)"
x("
1'"
1&"
x%"
x$"
x#"
x""
x!"
x~
x}
x|
0{
0z
xy
xx
xw
xv
xu
xt
xs
xr
0q
0p
xo
xn
xm
xl
xk
xj
xi
xh
1g
0f
xe
xd
xc
xb
xa
x`
x_
x^
1]
1\
x[
xZ
xY
xX
xW
xV
xU
xT
1S
1R
xQ
xP
xO
xN
xM
xL
xK
xJ
1I
0H
xG
xF
xE
xD
xC
xB
xA
x@
0?
1>
x=
x<
x;
x:
x9
x8
x7
x6
05
04
x3
x2
x1
x0
x/
x.
x-
0,
0+
0*
bx0 )
bx (
0'
b101011001111000 &
b1001000110100 %
b101011001111000 $
b1001000110100 #
x"
bx !
$end
#100
0=
0G
0y
0%"
0C"
0W"
0k"
0.
08
0<
0B
0L
0P
1V
1`
0j
0n
0t
0x
0~
0$"
1*"
04"
08"
0>"
0B"
1H"
0R"
0V"
0\"
0`"
0f"
0j"
03
02
#150
0/
09
1C
1M
1W
1a
1k
0u
0!"
1+"
15"
0?"
1I"
0S"
1]"
0g"
#200
01
0;
1E
1O
0Y
0c
1m
0w
0#"
0-"
17"
0A"
0K"
0U"
1_"
0i"
#300
0@
1^
1h
0|
0("
12"
0F"
1P"
0Z"
0"
06
07
1U
1_
0s
0}
1)"
0="
1G"
0Q"
0e"
b0x010x100x11xx000 )
0-
#400
0F
1d
1e
1o
0."
0/"
19"
0L"
0M"
0a"
bx0 !
bx0 (
00
#500
1D
1b
0l
0""
0,"
06"
0J"
1T"
1^"
bx110x000x01xx100 !
bx110x000x01xx100 (
0:
#600
0J
1r
1<"
0d"
0A
1i
13"
b101100111x0000 )
0["
#700
0Q
#800
1N
1v
1@"
b1101000101x1100 !
b1101000101x1100 (
0h"
#900
0T
b10110011100000 )
0K
#1000
0Z
0[
#1100
b110100010101100 !
b110100010101100 (
0X
